exponax/__init__.py
exponax/_base_stepper.py
exponax/_forced_stepper.py
exponax/_interpolation.py
exponax/_poisson.py
exponax/_repeated_stepper.py
exponax/_spectral.py
exponax/_utils.py
exponax/etdrk/__init__.py
exponax/etdrk/_base_etdrk.py
exponax/etdrk/_etdrk_0.py
exponax/etdrk/_etdrk_1.py
exponax/etdrk/_etdrk_2.py
exponax/etdrk/_etdrk_3.py
exponax/etdrk/_etdrk_4.py
exponax/etdrk/_utils.py
exponax/ic/__init__.py
exponax/ic/_base_ic.py
exponax/ic/_clamping.py
exponax/ic/_diffused_noise.py
exponax/ic/_discontinuities.py
exponax/ic/_gaussian_blob.py
exponax/ic/_gaussian_random_field.py
exponax/ic/_multi_channel.py
exponax/ic/_scaled.py
exponax/ic/_sine_waves_1d.py
exponax/ic/_truncated_fourier_series.py
exponax/metrics/__init__.py
exponax/metrics/_correlation.py
exponax/metrics/_derivative.py
exponax/metrics/_fourier.py
exponax/metrics/_spatial.py
exponax/metrics/_utils.py
exponax/nonlin_fun/__init__.py
exponax/nonlin_fun/_base.py
exponax/nonlin_fun/_convection.py
exponax/nonlin_fun/_general_nonlinear.py
exponax/nonlin_fun/_gradient_norm.py
exponax/nonlin_fun/_polynomial.py
exponax/nonlin_fun/_vorticity_convection.py
exponax/nonlin_fun/_zero.py
exponax/stepper/__init__.py
exponax/stepper/_advection.py
exponax/stepper/_advection_diffusion.py
exponax/stepper/_burgers.py
exponax/stepper/_diffusion.py
exponax/stepper/_dispersion.py
exponax/stepper/_hyper_diffusion.py
exponax/stepper/_korteweg_de_vries.py
exponax/stepper/_kuramoto_sivashinsky.py
exponax/stepper/_navier_stokes.py
exponax/stepper/generic/__init__.py
exponax/stepper/generic/_convection.py
exponax/stepper/generic/_gradient_norm.py
exponax/stepper/generic/_linear.py
exponax/stepper/generic/_nonlinear.py
exponax/stepper/generic/_polynomial.py
exponax/stepper/generic/_utils.py
exponax/stepper/generic/_vorticity_convection.py
exponax/stepper/reaction/__init__.py
exponax/stepper/reaction/_allen_cahn.py
exponax/stepper/reaction/_belousov_zhabotinsky.py
exponax/stepper/reaction/_cahn_hilliard.py
exponax-0.1.0.dist-info/LICENSE.txt
exponax-0.1.0.dist-info/METADATA
exponax-0.1.0.dist-info/WHEEL
exponax-0.1.0.dist-info/top_level.txt
exponax-0.1.0.dist-info/RECORD
