Metadata-Version: 2.1
Name: exponax
Version: 0.1.0
Summary: Efficient differentiable PDE solvers in JAX.
Author: Felix Koehler
Project-URL: repository, https://github.com/Ceyron/exponax
Keywords: jax,sciml,deep-learning,pde,etdrk
Requires-Python: ~=3.10
License-File: LICENSE.txt
Requires-Dist: jax >=0.4.13
Requires-Dist: jaxtyping >=0.2.20
Requires-Dist: typing-extensions >=4.5.0
Requires-Dist: equinox >=0.11.3
Requires-Dist: matplotlib >=3.8.1
